vap/__init__.py
vap/client.py
vap/exceptions.py
vap/models.py
vap_sdk-0.2.1.dist-info/METADATA
vap_sdk-0.2.1.dist-info/WHEEL
vap_sdk-0.2.1.dist-info/RECORD
